tvb/__init__.py
tvb/contrib/__init__.py
tvb/contrib/cosimulation/__init__.py
tvb/contrib/cosimulation/cosim_history.py
tvb/contrib/cosimulation/cosim_monitors.py
tvb/contrib/cosimulation/cosimulator.py
tvb/contrib/cosimulation/exception.py
tvb/contrib/from_articles/__init__.py
tvb/contrib/from_articles/region_deterministic_bnm_g2d_a.py
tvb/contrib/from_articles/region_deterministic_bnm_g2d_b.py
tvb/contrib/from_articles/region_deterministic_bnm_g2d_c.py
tvb/contrib/from_articles/region_deterministic_bnm_g2d_d.py
tvb/contrib/from_articles/region_deterministic_bnm_sj2d.py
tvb/contrib/from_articles/region_deterministic_bnm_sj3d_a.py
tvb/contrib/from_articles/region_deterministic_bnm_wc.py
tvb/contrib/from_articles/region_deterministic_bnm_wc_a.py
tvb/contrib/from_articles/region_deterministic_bnm_wc_b.py
tvb/contrib/from_articles/region_deterministic_bnm_wc_c.py
tvb/contrib/rateML/README.md
tvb/contrib/rateML/XML2model.py
tvb/contrib/rateML/__init__.py
tvb/contrib/rateML/rML_v0.xsd
tvb/contrib/rateML/tmpl8_cuda.py
tvb/contrib/rateML/tmpl8_driver.py
tvb/contrib/rateML/tmpl8_python.py
tvb/contrib/rateML/XMLmodels/__init__.py
tvb/contrib/rateML/XMLmodels/epileptor.xml
tvb/contrib/rateML/XMLmodels/kuramoto.xml
tvb/contrib/rateML/XMLmodels/model_template.xml
tvb/contrib/rateML/XMLmodels/montbrio.xml
tvb/contrib/rateML/XMLmodels/oscillator.xml
tvb/contrib/rateML/XMLmodels/rwongwang.xml
tvb/contrib/rateML/XMLmodels/rwongwang_deco.xml
tvb/contrib/rateML/XMLmodels/zerlaut.xml
tvb/contrib/rateML/generatedModels/__init__.py
tvb/contrib/rateML/generatedModels/epileptor.c
tvb/contrib/rateML/generatedModels/epileptor.py
tvb/contrib/rateML/generatedModels/kuramoto.c
tvb/contrib/rateML/generatedModels/kuramoto.py
tvb/contrib/rateML/generatedModels/montbrio.c
tvb/contrib/rateML/generatedModels/montbrio.py
tvb/contrib/rateML/generatedModels/montbrio_heun.c
tvb/contrib/rateML/generatedModels/oscillator.c
tvb/contrib/rateML/generatedModels/oscillator.py
tvb_contrib-2.9.1.dist-info/LICENSE
tvb_contrib-2.9.1.dist-info/METADATA
tvb_contrib-2.9.1.dist-info/WHEEL
tvb_contrib-2.9.1.dist-info/top_level.txt
tvb_contrib-2.9.1.dist-info/RECORD
