Metadata-Version: 2.1
Name: tvb-contrib
Version: 2.9.1
Summary: A package with TVB contributed additions to the simulator, useful for scripting.
Home-page: https://www.thevirtualbrain.org
Download-URL: https://github.com/the-virtual-brain/tvb-root
Author: Stuart Knock, Dionysios Perdikis, Paula Sanz Leon, Bogdan Valean, Marmaduke Woodman, Michiel van der Vlag
Author-email: tvb.admin@thevirtualbrain.org
License: GPL-3.0-or-later
Keywords: tvb brain simulator neuroscience contrib
License-File: LICENSE
Requires-Dist: tvb-library
Requires-Dist: xarray
Requires-Dist: scikit-learn
Requires-Dist: lxml
Requires-Dist: pylems
